{
  "type": "minecraft:crafting_shaped",
  "category": "misc",
  "pattern": [
    " # ",
    "###",
    "PW "
  ],
  "key": {
    "#": "minecraft:light_gray_wool",
    "P": "minecraft:pink_dye",
    "W": "minecraft:white_wool"
  },
  "result": {
    "id": "minecraft:feather",
    "count": 1,
    "components": {
      "minecraft:custom_model_data": {"strings": [ "gray_shark" ] },
      "minecraft:custom_name": { "text": "Gray Toy Shark", "italic": false, "color": "white" },
      "minecraft:lore": [
        { "text": "a.k.a. Blahaj", "italic": false, "color": "gray" }
      ],
      "minecraft:custom_data": { "blahaj_stamp": 1 },
      "minecraft:attribute_modifiers": [
        {
          "type": "minecraft:block_break_speed",
          "amount": -3.0,
          "operation": "add_multiplied_total",
          "slot": "mainhand",
          "id": "blahaj:zero_block_break_speed_main"
        },
        {
          "type": "minecraft:attack_damage",
          "amount": -1.0,
          "operation": "add_multiplied_total",
          "slot": "mainhand",
          "id": "blahaj:zero_attack_damage_main",
          "display": { "type": "override", "value": { "text": "-100% Attack Damage", "italic": false, "color": "dark_green" }}
        }
      ],
      "minecraft:equippable": {
        "slot": "head",
        "equip_sound": "minecraft:block.wool.step",
        "swappable": false
      }
    }
  }
}

